LICENSE
MANIFEST.in
README.md
pyproject.toml
setup.py
JFIO/__init__.py
JFIO.egg-info/PKG-INFO
JFIO.egg-info/SOURCES.txt
JFIO.egg-info/dependency_links.txt
JFIO.egg-info/top_level.txt
JFIO/ThirdParty/json.hpp
JFIO/ThirdParty/pybind11_json.hpp
JFIO/read/__init__.py
JFIO/read/readJSONFromFile.cpp
JFIO/write/__init__.py
JFIO/write/writeJSON2File.cpp