Metadata-Version: 2.1
Name: JFIO
Version: 1.0.3
Summary: JFIO (Json Fast Input Output) is a high-performance Python package for efficient reading and writing of JSON files.
Home-page: https://github.com/PabloIbannez/JFIO
Author-email: Pablo Ibáñez-Freire <p.ibanez.fre@gmail.com>
License: MIT License
Classifier: Development Status :: 5 - Production/Stable
Classifier: License :: OSI Approved :: MIT License
Classifier: Programming Language :: Python :: 3
Classifier: Programming Language :: Python :: 3.6
Classifier: Programming Language :: Python :: 3.7
Classifier: Programming Language :: Python :: 3.8
Classifier: Programming Language :: Python :: 3.9
Requires-Python: >=3.6
License-File: LICENSE
